LICENSE
MANIFEST.in
README.rst
setup.py
jsonrpc2_zeromq/__init__.py
jsonrpc2_zeromq/client.py
jsonrpc2_zeromq/common.py
jsonrpc2_zeromq/server.py
jsonrpc2_zeromq.egg-info/PKG-INFO
jsonrpc2_zeromq.egg-info/SOURCES.txt
jsonrpc2_zeromq.egg-info/dependency_links.txt
jsonrpc2_zeromq.egg-info/pbr.json
jsonrpc2_zeromq.egg-info/requires.txt
jsonrpc2_zeromq.egg-info/top_level.txt