Metadata-Version: 1.1
Name: jsonrpc2-zeromq
Version: 2.0.0
Summary: Library for JSON-RPC 2.0 over ZeroMQ
Home-page: https://github.com/dwb/python-jsonrpc2-zeromq
Author: Dan Brown
Author-email: dan@stompydan.net
License: License :: OSI Approved :: BSD License
Download-URL: https://github.com/dwb/jsonrpc2-zeromq-python/archive/v2.0.0.tar.gz
Platform: UNKNOWN
Classifier: Programming Language :: Python :: 2.7
Classifier: Programming Language :: Python :: 3.3
Classifier: Programming Language :: Python :: 3.4
Classifier: Development Status :: 5 - Production/Stable
Classifier: Intended Audience :: Developers
Classifier: License :: OSI Approved :: BSD License
